forma/__init__.py
forma/_nbdev.py
forma/detector.py
forma/judge.py
forma/utils.py
forma-0.2.2.dist-info/LICENSE
forma-0.2.2.dist-info/METADATA
forma-0.2.2.dist-info/WHEEL
forma-0.2.2.dist-info/entry_points.txt
forma-0.2.2.dist-info/top_level.txt
forma-0.2.2.dist-info/RECORD
