Metadata-Version: 2.1
Name: forma
Version: 0.2.2
Summary: Automatic format error detection on tabular data
Home-page: https://github.com/dpoulopoulos/forma/tree/master/
Author: Dimitris Poulopoulos
Author-email: dimitris.a.poulopoulos@gmail.com
License: Apache Software License 2.0
Keywords: error detection,machine learning
Platform: UNKNOWN
Classifier: Development Status :: 3 - Alpha
Classifier: Intended Audience :: Developers
Classifier: License :: OSI Approved :: Apache Software License
Classifier: Natural Language :: English
Classifier: Programming Language :: Python :: 3.6
Classifier: Programming Language :: Python :: 3.7
Classifier: Programming Language :: Python :: 3.8
Requires-Python: >=3.6
Requires-Dist: tqdm
Requires-Dist: pandas
Requires-Dist: nltk
